setup.cfg
setup.py
ciscospark/__init__.py
ciscospark/constants.py
ciscospark/core.py
ciscospark/exceptions.py
ciscospark.egg-info/PKG-INFO
ciscospark.egg-info/SOURCES.txt
ciscospark.egg-info/dependency_links.txt
ciscospark.egg-info/requires.txt
ciscospark.egg-info/top_level.txt