Metadata-Version: 1.1
Name: ciscospark
Version: 0.1.2
Summary: Python wrapper for Cisco Spark's REST API
Home-page: https://github.com/gnahckire/ciscospark-py
Author: Erik Chang
Author-email: gnahckire@gmail.com,erikchan@cisco.com
License: UNKNOWN
Download-URL: https://github.com/gnahckire/ciscospark-py/releases
Keywords: cisco,spark,ciscospark
Platform: UNKNOWN
